eventsourcing_axonserver/__init__.py
eventsourcing_axonserver/axonserver/__init__.py
eventsourcing_axonserver/factory.py
eventsourcing_axonserver/py.typed
eventsourcing_axonserver/recorders.py
eventsourcing_axonserver-0.1.5.dist-info/LICENSE
eventsourcing_axonserver-0.1.5.dist-info/WHEEL
eventsourcing_axonserver-0.1.5.dist-info/METADATA
eventsourcing_axonserver-0.1.5.dist-info/RECORD
