Metadata-Version: 2.1
Name: eventsourcing-axonserver
Version: 0.1.5
Summary: Python package for eventsourcing with Axon Server
Home-page: https://github.com/pyeventsourcing/eventsourcing-axonserver
License: BSD 3-Clause
Author: John Bywater
Author-email: john.bywater@appropriatesoftware.net
Requires-Python: >=3.7,<4.0
Classifier: Development Status :: 3 - Alpha
Classifier: License :: OSI Approved :: BSD License
Classifier: License :: Other/Proprietary License
Classifier: Programming Language :: Python
Classifier: Programming Language :: Python :: 3
Classifier: Programming Language :: Python :: 3.10
Classifier: Programming Language :: Python :: 3.7
Classifier: Programming Language :: Python :: 3.8
Classifier: Programming Language :: Python :: 3.9
Requires-Dist: axonclient (>=0.1.2,<0.2.0)
Requires-Dist: eventsourcing (>=9.2.12,<9.3.0)
Project-URL: Repository, https://github.com/pyeventsourcing/eventsourcing-axonserver
